IservMultiTabReportsLib/__init__.py
IservMultiTabReportsLib/index.py
IservMultiTabReportsLib/lib.py
iservmultitabreportslib-0.0.9.dist-info/licenses/LICENSE
iservmultitabreportslib-0.0.9.dist-info/METADATA
iservmultitabreportslib-0.0.9.dist-info/WHEEL
iservmultitabreportslib-0.0.9.dist-info/top_level.txt
iservmultitabreportslib-0.0.9.dist-info/RECORD
