Metadata-Version: 2.4
Name: IservMultiTabReportsLib
Version: 0.0.9
Summary: Для формирования xlsx отчета из нескольких csv файлов.
Author-email: "kirill.avtonomov" <kirill.avtonomov@yandex.ru>
License-Expression: MIT
Project-URL: Homepage, https://github.com/kirillva/MultiTabReportsLib
Project-URL: Issues, https://github.com/kirillva/MultiTabReportsLib/issues
Classifier: Programming Language :: Python :: 3
Classifier: Operating System :: OS Independent
Requires-Python: >=3.9
License-File: LICENSE
Dynamic: license-file
